[
  {
    "id": 1,
    "title": "Новости о технологиях",
    "description": "Последние новости из мира технологий и инноваций.",
    "content": "Сегодня компания Apple представила новый iPhone 15 с революционными функциями...",
    "category": "Технологии",
    "tags": ["технологии", "apple", "iphone"],
    "source": "TechCrunch",
    "date": "2023-10-01",
    "image": "https://picsum.photos/800/450?random=1",
    "likes": 120,
    "comments": [
      {
        "id": 1,
        "user": "Иван Иванов",
        "text": "Отличная статья! Жду новый iPhone.",
        "date": "2023-10-01T12:00:00Z"
      }
    ],
    "related": [2, 3]
  },
  {
    "id": 2,
    "title": "Криптовалюты на подъеме",
    "description": "Биткоин снова бьет рекорды.",
    "content": "Сегодня цена Deutsche eMark (DEM) — 0,003964 $. Объем торгов за 24 часа — 81,77 $. Цена увеличилась на 0,99% за последние 24 часа и увеличилась на 25,55% за последние 7 дней. Данные о рыночной капитализации Deutsche eMark недоступны, так как у нас нет информации о количестве токенов DEM в обращении.",
    "category": "Финансы",
    "tags": ["криптовалюты", "биткоин", "финансы"],
    "source": "CoinDesk",
    "date": "2023-10-02",
    "image": "https://picsum.photos/800/450?random=2",
    "likes": 85,
    "comments": [],
    "related": [1, 3]
  },
  {
    "id": 3,
    "title": "Новые тренды в моде",
    "description": "Осень 2023: что носить?",
    "content": "«Основная идея коллекции – использование положительного цветового влияния на психоэмоциональное состояние человека, а также интеграция искусства в повседневную жизнь. Я как художник и дизайнер полностью придерживаюсь постулата Йоганеса Иттена, что цвет — это жизнь, и мир без цвета был бы мертвым для нас. В своем творчестве я много лет занималась исследованием цветов и цветовых сочетаний в нефигуративной живописи.",
    "category": "Мода",
    "tags": ["мода", "стиль", "осень"],
    "source": "Vogue",
    "date": "2023-10-03",
    "image": "https://picsum.photos/800/450?random=3",
    "likes": 45,
    "comments": [
      {
        "id": 2,
        "user": "Мария Петрова",
        "text": "Интересные тренды, спасибо за статью!",
        "date": "2023-10-03T10:00:00Z"
      }
    ],
    "related": [1, 2]
  },
  {
    "id": 4,
    "title": "Искусственный интеллект в медицине",
    "description": "Как ИИ меняет здравоохранение.",
    "content": "Искусственный интеллект помогает врачам ставить диагнозы...",
    "category": "Технологии",
    "tags": ["искусственный интеллект", "медицина", "технологии"],
    "source": "Wired",
    "date": "2023-10-04",
    "image": "https://picsum.photos/800/450?random=4",
    "likes": 95,
    "comments": [],
    "related": [1, 5]
  },
  {
    "id": 5,
    "title": "Новый закон о налогах",
    "description": "Изменения в налоговом кодексе с 2024 года.",
    "content": "Правительство утвердило новый закон о налогах...",
    "category": "Финансы",
    "tags": ["налоги", "финансы", "закон"],
    "source": "Forbes",
    "date": "2023-10-05",
    "image": "https://picsum.photos/800/450?random=5",
    "likes": 60,
    "comments": [],
    "related": [2, 6]
  },
  {
    "id": 6,
    "title": "Космические путешествия становятся ближе",
    "description": "Компания SpaceX планирует запуск туристических полетов.",
    "content": "SpaceX объявила о планах запустить туристические полеты на орбиту...",
    "category": "Технологии",
    "tags": ["космос", "spacex", "технологии"],
    "source": "The Verge",
    "date": "2023-10-06",
    "image": "https://picsum.photos/800/450?random=6",
    "likes": 110,
    "comments": [
      {
        "id": 3,
        "user": "Дмитрий Соколов",
        "text": "Мечтаю полететь в космос!",
        "date": "2023-10-06T09:00:00Z"
      }
    ],
    "related": [1, 4]
  },
  {
    "id": 7,
    "title": "Электромобили будущего",
    "description": "Tesla представила новый концепт электромобиля.",
    "content": "Компания Tesla анонсировала новый электромобиль с автономным управлением...",
    "category": "Технологии",
    "tags": ["электромобили", "tesla", "технологии"],
    "source": "TechRadar",
    "date": "2023-10-07",
    "image": "https://picsum.photos/800/450?random=7",
    "likes": 75,
    "comments": [],
    "related": [6, 8]
  },
  {
    "id": 8,
    "title": "Здоровый образ жизни",
    "description": "Топ-5 советов для здорового образа жизни в 2023 году.",
    "content": "Эксперты делятся советами, как оставаться здоровым...",
    "category": "Здоровье",
    "tags": ["здоровье", "образ жизни", "советы"],
    "source": "HealthLine",
    "date": "2023-10-08",
    "image": "https://picsum.photos/800/450?random=8",
    "likes": 50,
    "comments": [],
    "related": [9, 10]
  },
  {
    "id": 9,
    "title": "Игровая индустрия в 2023 году",
    "description": "Новые тренды в игровой индустрии.",
    "content": "Игровая индустрия продолжает расти...",
    "category": "Игры",
    "tags": ["игры", "индустрия", "тренды"],
    "source": "IGN",
    "date": "2023-10-09",
    "image": "https://picsum.photos/800/450?random=9",
    "likes": 90,
    "comments": [],
    "related": [7, 10]
  },
  {
    "id": 10,
    "title": "Кибербезопасность в современном мире",
    "description": "Как защитить свои данные в 2023 году.",
    "content": "Эксперты рассказывают о новых угрозах и способах защиты...",
    "category": "Технологии",
    "tags": ["кибербезопасность", "технологии", "защита данных"],
    "source": "Wired",
    "date": "2023-10-10",
    "image": "https://picsum.photos/800/450?random=10",
    "likes": 80,
    "comments": [],
    "related": [6, 9]
  }
]
